numba_passthru/__init__.py
numba_passthru/numba_passthru.py
numba_passthru/test/test_passthru.py
numba_passthru-0.3.0.dist-info/LICENSE
numba_passthru-0.3.0.dist-info/WHEEL
numba_passthru-0.3.0.dist-info/METADATA
numba_passthru-0.3.0.dist-info/RECORD
