Metadata-Version: 2.1
Name: numba-passthru
Version: 0.3.0
Summary: Stand-alone package for Numba passthrough types until PR 3640 has landed
Home-page: https://github.com/asodeur/numba-passthru
Keywords: numba
Author: Andreas Sodeur
Author-email: andreas.sodeur@rwe.com
Requires-Python: >=3.6
Classifier: Development Status :: 4 - Beta
Classifier: Intended Audience :: Developers
Classifier: License :: OSI Approved :: BSD License
Classifier: Operating System :: OS Independent
Classifier: Programming Language :: Python
Classifier: Programming Language :: Python :: 2.7
Classifier: Programming Language :: Python :: 3
Classifier: Programming Language :: Python :: 3.4
Classifier: Programming Language :: Python :: 3.5
Classifier: Programming Language :: Python :: 3.6
Classifier: Programming Language :: Python :: 3.7
Classifier: Programming Language :: Python :: 3.8
Classifier: Topic :: Software Development :: Compilers
Requires-Dist: numba (>=0.51.2)
